magic_pdf/__init__.py
magic_pdf/pdf_parse_union_core_v2.py
magic_pdf/config/__init__.py
magic_pdf/config/constants.py
magic_pdf/config/drop_reason.py
magic_pdf/config/drop_tag.py
magic_pdf/config/enums.py
magic_pdf/config/exceptions.py
magic_pdf/config/make_content_config.py
magic_pdf/config/model_block_type.py
magic_pdf/config/ocr_content_type.py
magic_pdf/data/__init__.py
magic_pdf/data/batch_build_dataset.py
magic_pdf/data/dataset.py
magic_pdf/data/read_api.py
magic_pdf/data/schemas.py
magic_pdf/data/utils.py
magic_pdf/data/data_reader_writer/__init__.py
magic_pdf/data/data_reader_writer/base.py
magic_pdf/data/data_reader_writer/filebase.py
magic_pdf/data/data_reader_writer/multi_bucket_s3.py
magic_pdf/data/data_reader_writer/s3.py
magic_pdf/data/io/__init__.py
magic_pdf/data/io/base.py
magic_pdf/data/io/http.py
magic_pdf/data/io/s3.py
magic_pdf/dict2md/__init__.py
magic_pdf/dict2md/ocr_mkcontent.py
magic_pdf/filter/__init__.py
magic_pdf/filter/pdf_classify_by_type.py
magic_pdf/filter/pdf_meta_scan.py
magic_pdf/integrations/__init__.py
magic_pdf/integrations/rag/__init__.py
magic_pdf/integrations/rag/api.py
magic_pdf/integrations/rag/type.py
magic_pdf/integrations/rag/utils.py
magic_pdf/libs/__init__.py
magic_pdf/libs/boxbase.py
magic_pdf/libs/clean_memory.py
magic_pdf/libs/commons.py
magic_pdf/libs/config_reader.py
magic_pdf/libs/convert_utils.py
magic_pdf/libs/coordinate_transform.py
magic_pdf/libs/draw_bbox.py
magic_pdf/libs/hash_utils.py
magic_pdf/libs/json_compressor.py
magic_pdf/libs/language.py
magic_pdf/libs/local_math.py
magic_pdf/libs/markdown_utils.py
magic_pdf/libs/path_utils.py
magic_pdf/libs/pdf_check.py
magic_pdf/libs/pdf_image_tools.py
magic_pdf/libs/performance_stats.py
magic_pdf/libs/safe_filename.py
magic_pdf/libs/version.py
magic_pdf/model/__init__.py
magic_pdf/model/batch_analyze.py
magic_pdf/model/doc_analyze_by_custom_model.py
magic_pdf/model/magic_model.py
magic_pdf/model/model_list.py
magic_pdf/model/pdf_extract_kit.py
xh_pdf_parser-1.3.1.2.dist-info/METADATA
xh_pdf_parser-1.3.1.2.dist-info/WHEEL
xh_pdf_parser-1.3.1.2.dist-info/entry_points.txt
xh_pdf_parser-1.3.1.2.dist-info/top_level.txt
xh_pdf_parser-1.3.1.2.dist-info/RECORD
